torchprep/__init__.py
torchprep/main.py
torchprep-0.1.0.dist-info/entry_points.txt
torchprep-0.1.0.dist-info/WHEEL
torchprep-0.1.0.dist-info/METADATA
torchprep-0.1.0.dist-info/RECORD
