Metadata-Version: 2.1
Name: torchprep
Version: 0.1.0
Summary: The easiest way to prepare Pytorch models for inference
Author: Mark Saroufim
Author-email: marksaroufim@fb.com
Requires-Python: >=3.8,<4.0
Classifier: Programming Language :: Python :: 3
Classifier: Programming Language :: Python :: 3.10
Classifier: Programming Language :: Python :: 3.8
Classifier: Programming Language :: Python :: 3.9
Requires-Dist: torch (>=1.9.1,<2.0.0)
Requires-Dist: tqdm (>=4.62.3,<5.0.0)
Requires-Dist: typer[all] (>=0.4.0,<0.5.0)
